<?xml version="1.0" encoding="utf-8"?>
<List xmlns:ows="Microsoft SharePoint" Title="DocumentNumbers" FolderCreation="FALSE" Direction="$Resources:Direction;" Url="Lists/TCSU-DocumentNumbers" BaseType="0" xmlns="http://schemas.microsoft.com/sharepoint/">
  <MetaData>
    <ContentTypes>
      <ContentTypeRef ID="0x01">
        <Folder TargetName="Item" />
      </ContentTypeRef>
      <ContentTypeRef ID="0x0120" />
    </ContentTypes>
    <Fields>
      <Field ID="{433FC353-BEAD-4015-B201-6370CDA554DB}"
        Type="Number"
        Group="TCSU Columns"
        DisplayName="Section"
        Name="Section"
        Required="true"/>

      


      <Field ID="{fa564e0f-0c70-4ab9-b863-0177e6ddd247}" Name="Title" DisplayName="CDRL List" Type="Text" MaxLength="50" />

      <Field ID="{2C019D0E-D182-4F1D-8637-172F88D43FF1}"
       Type="Text"
       Group="TCSU Columns"
       DisplayName="Alstom Document Description"
       Name="AlstomDocumentDescription"
       Required="true"/>

      <Field ID="{3F420069-E190-4616-B3FA-207B1DBF9FCC}"
            Type="Text"
            Group="TCSU Columns"
            DisplayName="SubSystem"
            Name="SubSystem"
            Required="true"/>
      
    </Fields>
    <Views>
      <View BaseViewID="0" Type="HTML" MobileView="TRUE" TabularView="FALSE">
        <Toolbar Type="Standard" />
        <XslLink Default="TRUE">main.xsl</XslLink>
        <RowLimit Paged="TRUE">30</RowLimit>
        <ViewFields>
          <FieldRef Name="LinkTitleNoMenu"></FieldRef>
        </ViewFields>
        <Query>
          <OrderBy>
            <FieldRef Name="Modified" Ascending="FALSE"></FieldRef>
          </OrderBy>
        </Query>
        <ParameterBindings>
          <ParameterBinding Name="AddNewAnnouncement" Location="Resource(wss,addnewitem)" />
          <ParameterBinding Name="NoAnnouncements" Location="Resource(wss,noXinviewofY_LIST)" />
          <ParameterBinding Name="NoAnnouncementsHowTo" Location="Resource(wss,noXinviewofY_ONET_HOME)" />
        </ParameterBindings>
      </View>
      <View BaseViewID="1" Type="HTML" WebPartZoneID="Main" DisplayName="$Resources:core,objectiv_schema_mwsidcamlidC24;" DefaultView="TRUE" MobileView="TRUE" MobileDefaultView="TRUE" SetupPath="pages\viewpage.aspx" ImageUrl="/_layouts/images/generic.png" Url="AllItems.aspx">
        <Toolbar Type="Standard" />
        <XslLink Default="TRUE">main.xsl</XslLink>
        <RowLimit Paged="TRUE">30</RowLimit>
        <ViewFields>
          <FieldRef Name="Attachments"></FieldRef>
          <FieldRef Name="LinkTitle"></FieldRef>
        </ViewFields>
        <Query>
          <OrderBy>
            <FieldRef Name="ID"></FieldRef>
          </OrderBy>
        </Query>
        <ParameterBindings>
          <ParameterBinding Name="NoAnnouncements" Location="Resource(wss,noXinviewofY_LIST)" />
          <ParameterBinding Name="NoAnnouncementsHowTo" Location="Resource(wss,noXinviewofY_DEFAULT)" />
        </ParameterBindings>
      </View>
    </Views>
    <Forms>
      <Form Type="DisplayForm" Url="DispForm.aspx" SetupPath="pages\form.aspx" WebPartZoneID="Main" />
      <Form Type="EditForm" Url="EditForm.aspx" SetupPath="pages\form.aspx" WebPartZoneID="Main" />
      <Form Type="NewForm" Url="NewForm.aspx" SetupPath="pages\form.aspx" WebPartZoneID="Main" />
    </Forms>
  </MetaData>
</List>